{
  "results": {
    "http://humanbehaviourchange.org/ontology/bcio.owl": {
      "graph_id": "http://humanbehaviourchange.org/ontology/bcio.owl",
      "prov_pack": {
        "invalid_luids": {
          "http://purl.obolibrary.org/obo/ENVO_00000010": [
            "MA:ma"
          ],
          "http://purl.obolibrary.org/obo/ENVO_00000070": [
            "MA:ma"
          ]
        },
        "known_prefixes": {},
        "label": "Provenance Xrefs",
        "malformed_curies": {},
        "noncanonical_prefixes": {},
        "unknown_prefixes": {
          "GOC": {
            "http://purl.obolibrary.org/obo/GO_0003008": "GOC:mtg_cardio",
            "http://purl.obolibrary.org/obo/GO_0007610": "GOC:jl",
            "http://purl.obolibrary.org/obo/GO_0007611": "GOC:jid",
            "http://purl.obolibrary.org/obo/GO_0007613": "GOC:curators",
            "http://purl.obolibrary.org/obo/GO_0008150": "GOC:pdt",
            "http://purl.obolibrary.org/obo/GO_0032501": "GOC:tb",
            "http://purl.obolibrary.org/obo/GO_0050877": "GOC:mtg_cardio",
            "http://purl.obolibrary.org/obo/GO_0098596": "GOC:dos"
          },
          "USGS": {
            "http://purl.obolibrary.org/obo/ENVO_00000064": "USGS:SDTS",
            "http://purl.obolibrary.org/obo/ENVO_00000109": "USGS:SDTS"
          },
          "url": {
            "http://purl.obolibrary.org/obo/IAO_0000115": "url:http://purl.obolibrary.org/obo/iao.owl",
            "http://www.geneontology.org/formats/oboInOwl#hasAlternativeId": "url:http://www.geneontology.org/formats/oboInOwl#hasAlternativeId",
            "http://www.geneontology.org/formats/oboInOwl#hasOBONamespace": "url:http://www.geneontology.org/formats/oboInOwl#hasOBONamespace",
            "http://www.geneontology.org/formats/oboInOwl#id": "url:http://purl.obolibrary.org/obo/IAO_0020000",
            "http://www.geneontology.org/formats/oboInOwl#inSubset": "url:http://www.geneontology.org/formats/oboInOwl#inSubset",
            "http://www.w3.org/2000/01/rdf-schema#comment": "url:http://www.w3.org/2000/01/rdf-schema#comment",
            "http://www.w3.org/2000/01/rdf-schema#label": "url:http://www.w3.org/2000/01/rdf-schema#label"
          }
        }
      },
      "synonym_pack": {
        "invalid_luids": {
          "http://purl.obolibrary.org/obo/ENVO_00000064": [
            "Geonames:feature"
          ],
          "http://purl.obolibrary.org/obo/ENVO_00000091": [
            "Geonames:feature"
          ],
          "http://purl.obolibrary.org/obo/ENVO_00000109": [
            "Geonames:feature"
          ],
          "http://purl.obolibrary.org/obo/ENVO_00000111": [
            "Geonames:feature"
          ]
        },
        "known_prefixes": {},
        "label": "Synonym Xrefs",
        "malformed_curies": {},
        "noncanonical_prefixes": {},
        "unknown_prefixes": {
          "ADL": {
            "http://purl.obolibrary.org/obo/ENVO_00000064": "ADL:FTT",
            "http://purl.obolibrary.org/obo/ENVO_00000091": "ADL:FTT",
            "http://purl.obolibrary.org/obo/ENVO_00000109": "ADL:FTT",
            "http://purl.obolibrary.org/obo/ENVO_00000191": "ADL:FTT"
          },
          "Getty": {
            "http://purl.obolibrary.org/obo/ENVO_00000064": "Getty:TGN",
            "http://purl.obolibrary.org/obo/ENVO_00000106": "Getty:TGN",
            "http://purl.obolibrary.org/obo/ENVO_00000109": "Getty:TGN",
            "http://purl.obolibrary.org/obo/ENVO_00000111": "Getty:TGN"
          },
          "NASA": {
            "http://purl.obolibrary.org/obo/ENVO_00000091": "NASA:earthrealm"
          },
          "USGS": {
            "http://purl.obolibrary.org/obo/ENVO_00000064": "USGS:SDTS",
            "http://purl.obolibrary.org/obo/ENVO_00000091": "USGS:SDTS",
            "http://purl.obolibrary.org/obo/ENVO_00000106": "USGS:SDTS",
            "http://purl.obolibrary.org/obo/ENVO_00000109": "USGS:SDTS"
          }
        }
      },
      "version": "http://humanbehaviourchange.org/ontology/bcio.owl/2025-05-01",
      "xref_pack": {
        "invalid_luids": {
          "http://purl.obolibrary.org/obo/ENVO_00000064": [
            "Geonames:R",
            "Geonames:R.RD",
            "Geonames:R.ST"
          ],
          "http://purl.obolibrary.org/obo/ENVO_00000091": [
            "Geonames:T.BCH",
            "Geonames:T.BCHS"
          ],
          "http://purl.obolibrary.org/obo/ENVO_00000109": [
            "Geonames:V.GRVPN"
          ],
          "http://purl.obolibrary.org/obo/ENVO_00000111": [
            "Geonames:V.FRST"
          ]
        },
        "known_prefixes": {},
        "label": "Node Xrefs",
        "malformed_curies": {},
        "noncanonical_prefixes": {
          "SCTID": {
            "http://purl.obolibrary.org/obo/UBERON_0000061": "SCTID:362889002"
          }
        },
        "unknown_prefixes": {
          "GAID": {
            "http://purl.obolibrary.org/obo/UBERON_0000061": "GAID:781"
          }
        }
      }
    }
  }
}