{
  "results": {
    "https://raw.githubusercontent.com/enpadasi/Ontology-for-Nutritional-Studies/master/ons.owl": {
      "graph_id": "https://raw.githubusercontent.com/enpadasi/Ontology-for-Nutritional-Studies/master/ons.owl",
      "prov_pack": {
        "invalid_luids": {},
        "known_prefixes": {},
        "label": "Provenance Xrefs",
        "malformed_curies": {},
        "noncanonical_prefixes": {},
        "unknown_prefixes": {}
      },
      "synonym_pack": {
        "invalid_luids": {},
        "known_prefixes": {},
        "label": "Synonym Xrefs",
        "malformed_curies": {},
        "noncanonical_prefixes": {},
        "unknown_prefixes": {}
      },
      "version": "https://raw.githubusercontent.com/enpadasi/Ontology-for-Nutritional-Studies/releases/download/v2024-07-03/ons.owl",
      "xref_pack": {
        "invalid_luids": {},
        "known_prefixes": {},
        "label": "Node Xrefs",
        "malformed_curies": {},
        "noncanonical_prefixes": {},
        "unknown_prefixes": {}
      }
    }
  }
}